stak/__init__.py
stak/stak.py
stak/commands/__init__.py
stak/commands/Create.py
stak/commands/Devices.py
stak/util/__init__.py
stak/util/Config.py
stak/util/DD.py
stak/util/Device.py
stak/util/OS.py
stak/util/Project.py
stak/util/Util.py
stak-0.1.2.dist-info/DESCRIPTION.rst
stak-0.1.2.dist-info/entry_points.txt
stak-0.1.2.dist-info/METADATA
stak-0.1.2.dist-info/metadata.json
stak-0.1.2.dist-info/RECORD
stak-0.1.2.dist-info/top_level.txt
stak-0.1.2.dist-info/WHEEL
