Metadata-Version: 2.0
Name: stak
Version: 0.1.2
Summary: stak cli tool
Home-page: http://nextthing.co/stak.html
Author: Next Thing Co.
Author-email: Ahoyahoy@nextthing.co
License: MIT
Keywords: sample setuptools development
Platform: UNKNOWN
Classifier: Development Status :: 3 - Alpha
Classifier: Intended Audience :: Developers
Classifier: Topic :: Software Development :: Build Tools
Classifier: License :: OSI Approved :: MIT License
Classifier: Programming Language :: Python :: 2
Classifier: Programming Language :: Python :: 2.7
Requires-Dist: Click
Requires-Dist: PyYAML
Requires-Dist: zeroconf
Requires-Dist: jinja2 (<2.8,>=2.7)
Requires-Dist: honcho
Requires-Dist: honcho[export]
